api_insee/__init__.py
api_insee/api.py
api_insee/conf.py
api_insee/criteria/__init__.py
api_insee/criteria/base.py
api_insee/criteria/field.py
api_insee/criteria/field_exact.py
api_insee/criteria/list.py
api_insee/criteria/periodic.py
api_insee/criteria/periodic_field.py
api_insee/criteria/range.py
api_insee/criteria/raw.py
api_insee/exeptions/__init__.py
api_insee/exeptions/auth_exeption.py
api_insee/exeptions/params_exeption.py
api_insee/exeptions/request_exeption.py
api_insee/request/__init__.py
api_insee/request/request.py
api_insee/request/request_entreprises.py
api_insee/request/request_token.py
api_insee/request/url_params.py
api_insee/utils/__init__.py
api_insee/utils/auth_service.py
api_insee/utils/client_credentials.py
api_insee/utils/client_token.py
api_insee-1.5.dist-info/AUTHORS.rst
api_insee-1.5.dist-info/LICENSE.txt
api_insee-1.5.dist-info/METADATA
api_insee-1.5.dist-info/WHEEL
api_insee-1.5.dist-info/top_level.txt
api_insee-1.5.dist-info/RECORD
