Metadata-Version: 2.1
Name: api-insee
Version: 1.5
Summary: Python helper to request Sirene Api on api.insee.fr
Home-page: https://github.com/sne3ks/api_insee
Author: Lenselle Nicolas
Author-email: lenselle.nicolas@gmail.com
License: mit
Platform: any
Classifier: Development Status :: 4 - Beta
Classifier: Programming Language :: Python
Provides-Extra: testing
Requires-Dist: pytest ; extra == 'testing'
Requires-Dist: pytest-cov ; extra == 'testing'
